setup.py
pymetrics/__init__.py
pymetrics/pds_redis.py
python_metrics.egg-info/PKG-INFO
python_metrics.egg-info/SOURCES.txt
python_metrics.egg-info/dependency_links.txt
python_metrics.egg-info/requires.txt
python_metrics.egg-info/top_level.txt