Metadata-Version: 1.0
Name: python-metrics
Version: 0.2
Summary: simple python metrics (gauges, histograms, meters, timers) to gather data from your application
Home-page: https://github.com/gleicon/pymetrics
Author: Gleicon Moraes
Author-email: gleicon@gmail.com
License: UNKNOWN
Keywords: metrics redis
Platform: UNKNOWN
